<parameters>
  <projectType>坡面径流模型</projectType>
  <模型参数>
    <考虑水流方向>false</考虑水流方向>
    <考虑汇流>false</考虑汇流>
    <考虑沟道工程>false</考虑沟道工程>
    <考虑养分流失>false</考虑养分流失>
    <考虑沟道>true</考虑沟道>
    <考虑道路>false</考虑道路>
    <洪峰流量调整系数>0</洪峰流量调整系数>
    <出口流量过程计算方法>马斯京根法</出口流量过程计算方法>
    <时间设置>
      <开始时间>2022/12/7 星期三 9:27:19</开始时间>
      <终止时间>2022/12/7 星期三 9:27:19</终止时间>
    </时间设置>
    <流量过程计算参数设置 />
    <投影设置 />
    <几何设置>
      <宽>0</宽>
      <高>0</高>
      <X0>0</X0>
      <Y0>0</Y0>
      <分辨率>0</分辨率>
    </几何设置>
    <移动阈值>
    </移动阈值>
    <修正统计站点位置>false</修正统计站点位置>
    <输出年降雨量>False</输出年降雨量>
    <输出年径流深>False</输出年径流深>
  </模型参数>
  <WatershedBoundary>
    <path>
    </path>
  </WatershedBoundary>
  <dem>
    <path>
    </path>
  </dem>
  <沟道>
    <字段名称>
      <沟道编码>
      </沟道编码>
    </字段名称>
    <路径>
    </路径>
    <矢量>
      <属性组 />
    </矢量>
  </沟道>
  <道路>
    <道路编码字段名称>
    </道路编码字段名称>
    <路径>
    </路径>
    <属性组 />
  </道路>
  <降雨>
    <path>
    </path>
  </降雨>
  <土壤>
    <path>
    </path>
    <土壤类型字段名称>
    </土壤类型字段名称>
    <属性组 />
    <编码组 />
  </土壤>
  <土地利用>
    <path>
    </path>
    <土地利用类型字段名称>
    </土地利用类型字段名称>
    <属性组 />
    <编码组 />
  </土地利用>
  <工程措施因子>
    <path>
    </path>
    <土地利用类型字段名称>
    </土地利用类型字段名称>
    <属性组 />
    <编码组 />
  </工程措施因子>
  <生物措施因子>
    <path>
    </path>
    <土地利用类型字段名称>
    </土地利用类型字段名称>
    <属性组 />
    <编码组 />
  </生物措施因子>
  <耕作措施因子>
    <path>
    </path>
    <土地利用类型字段名称>
    </土地利用类型字段名称>
    <属性组 />
    <编码组 />
  </耕作措施因子>
  <SCSCN>
    <类型>SoilLanduseCombination</类型>
    <栅格路径>
    </栅格路径>
    <输入路径>
    </输入路径>
    <值列表 />
  </SCSCN>
  <沟道工程>
    <字段名称>
      <沟道工程编码>
      </沟道工程编码>
    </字段名称>
    <矢量路径>
    </矢量路径>
    <移动阈值>
    </移动阈值>
    <修正沟道工程栅格>false</修正沟道工程栅格>
    <矢量>
      <属性组 />
    </矢量>
  </沟道工程>
</parameters>